WhereDoIHaveAnAccount/__init__.py
WhereDoIHaveAnAccount/cli.py
WhereDoIHaveAnAccount/scraper.py
wheredoihaveanaccount-1.4.3.dist-info/entry_points.txt
wheredoihaveanaccount-1.4.3.dist-info/LICENSE
wheredoihaveanaccount-1.4.3.dist-info/WHEEL
wheredoihaveanaccount-1.4.3.dist-info/METADATA
wheredoihaveanaccount-1.4.3.dist-info/RECORD
