Metadata-Version: 2.1
Name: WhereDoIHaveAnAccount
Version: 1.4.3
Summary: Simple tool to find out where you have accounts.
Author: Timo Kühne
Requires-Python: >=3.6.1
Classifier: Operating System :: OS Independent
Classifier: Programming Language :: Python :: 3
Classifier: Programming Language :: Python
Classifier: License :: OSI Approved :: MIT License
Classifier: Programming Language :: Python :: 3 :: Only
Classifier: Programming Language :: Python :: 3.9
Classifier: Programming Language :: Python :: 3.8
Classifier: Programming Language :: Python :: 3.7
Classifier: Programming Language :: Python :: 3.6
Requires-Dist: imap-tools>=0.5
Requires-Dist: requests>=2.24
Requires-Dist: email_validator >=1.1.1
Requires-Dist: pandas >=1.0.3
Requires-Dist: feather-format >=0.3
Requires-Dist: nltk >=3.4.5
Requires-Dist: sklearn
Requires-Dist: pytest >=6.2.4 ; extra == "test"
Requires-Dist: pytest-cov >=2.12.0 ; extra == "test"
Requires-Dist: tox >=3.14.0 ; extra == "test"
Project-URL: Documentation, https://github.com/H3nkl3r/WhereDoIHaveAnAccount/wiki
Project-URL: Source, https://github.com/h3nkl3r/wheredoihaveanaccount
Provides-Extra: test
